[
  {
    "candidate": "harness/round2/assembled/r2-02-comb6.svelte",
    "pass": true,
    "gzip": 2345,
    "min": 6518,
    "behaviorPass": true,
    "cssPass": true,
    "total": 18,
    "failed": [],
    "error": null,
    "name": "r2-02-comb6"
  },
  {
    "candidate": "harness/round2/assembled/r2-04b.svelte",
    "pass": true,
    "gzip": 2342,
    "min": 6468,
    "behaviorPass": true,
    "cssPass": true,
    "total": 18,
    "failed": [],
    "error": null,
    "name": "r2-04b"
  },
  {
    "candidate": "harness/round2/assembled/r2-04c.svelte",
    "pass": true,
    "gzip": 2331,
    "min": 6438,
    "behaviorPass": true,
    "cssPass": true,
    "total": 18,
    "failed": [],
    "error": null,
    "name": "r2-04c"
  },
  {
    "candidate": "harness/round2/assembled/r2-04d.svelte",
    "pass": true,
    "gzip": 2337,
    "min": 6412,
    "behaviorPass": true,
    "cssPass": true,
    "total": 18,
    "failed": [],
    "error": null,
    "name": "r2-04d"
  },
  {
    "candidate": "harness/round2/assembled/r2-06-E.svelte",
    "pass": true,
    "gzip": 2344,
    "min": 6520,
    "behaviorPass": true,
    "cssPass": true,
    "total": 18,
    "failed": [],
    "error": null,
    "name": "r2-06-E"
  },
  {
    "candidate": "harness/round2/assembled/r2-07L.svelte",
    "pass": true,
    "gzip": 2332,
    "min": 6479,
    "behaviorPass": true,
    "cssPass": true,
    "total": 18,
    "failed": [],
    "error": null,
    "name": "r2-07L"
  },
  {
    "candidate": "harness/round2/assembled/r2-07h.svelte",
    "pass": true,
    "gzip": 2343,
    "min": 6487,
    "behaviorPass": true,
    "cssPass": true,
    "total": 18,
    "failed": [],
    "error": null,
    "name": "r2-07h"
  },
  {
    "candidate": "harness/round2/assembled/r2-07i1.svelte",
    "pass": true,
    "gzip": 2341,
    "min": 6493,
    "behaviorPass": true,
    "cssPass": true,
    "total": 18,
    "failed": [],
    "error": null,
    "name": "r2-07i1"
  },
  {
    "candidate": "harness/round2/assembled/r2-07i2.svelte",
    "pass": true,
    "gzip": 2345,
    "min": 6478,
    "behaviorPass": true,
    "cssPass": true,
    "total": 18,
    "failed": [],
    "error": null,
    "name": "r2-07i2"
  },
  {
    "candidate": "harness/round2/assembled/r2-07i3.svelte",
    "pass": true,
    "gzip": 2345,
    "min": 6485,
    "behaviorPass": true,
    "cssPass": true,
    "total": 18,
    "failed": [],
    "error": null,
    "name": "r2-07i3"
  },
  {
    "candidate": "harness/round2/assembled/r2-07j1.svelte",
    "pass": true,
    "gzip": 2339,
    "min": 6495,
    "behaviorPass": true,
    "cssPass": true,
    "total": 18,
    "failed": [],
    "error": null,
    "name": "r2-07j1"
  },
  {
    "candidate": "harness/round2/assembled/r2-07j2.svelte",
    "pass": true,
    "gzip": 2339,
    "min": 6489,
    "behaviorPass": true,
    "cssPass": true,
    "total": 18,
    "failed": [],
    "error": null,
    "name": "r2-07j2"
  },
  {
    "candidate": "harness/round2/assembled/r2-07k.svelte",
    "pass": true,
    "gzip": 2337,
    "min": 6491,
    "behaviorPass": true,
    "cssPass": true,
    "total": 18,
    "failed": [],
    "error": null,
    "name": "r2-07k"
  },
  {
    "candidate": "harness/round2/assembled/r2-07m.svelte",
    "pass": true,
    "gzip": 2329,
    "min": 6443,
    "behaviorPass": true,
    "cssPass": true,
    "total": 18,
    "failed": [],
    "error": null,
    "name": "r2-07m"
  },
  {
    "candidate": "harness/round2/assembled/r2-07n1.svelte",
    "pass": true,
    "gzip": 2329,
    "min": 6443,
    "behaviorPass": true,
    "cssPass": true,
    "total": 18,
    "failed": [],
    "error": null,
    "name": "r2-07n1"
  },
  {
    "candidate": "harness/round2/assembled/r2-07n2.svelte",
    "pass": true,
    "gzip": 2327,
    "min": 6441,
    "behaviorPass": true,
    "cssPass": true,
    "total": 18,
    "failed": [],
    "error": null,
    "name": "r2-07n2"
  },
  {
    "candidate": "harness/round2/assembled/r2-08-j1.svelte",
    "pass": true,
    "gzip": 2327,
    "min": 6470,
    "behaviorPass": true,
    "cssPass": true,
    "total": 18,
    "failed": [],
    "error": null,
    "name": "r2-08-j1"
  },
  {
    "candidate": "harness/round2/assembled/r2-09-f.svelte",
    "pass": true,
    "gzip": 2335,
    "min": 6471,
    "behaviorPass": true,
    "cssPass": true,
    "total": 18,
    "failed": [],
    "error": null,
    "name": "r2-09-f"
  },
  {
    "candidate": "harness/round2/assembled/r2-09-h.svelte",
    "pass": true,
    "gzip": 2330,
    "min": 6466,
    "behaviorPass": true,
    "cssPass": true,
    "total": 18,
    "failed": [],
    "error": null,
    "name": "r2-09-h"
  },
  {
    "candidate": "harness/round2/assembled/r2-10-v10.svelte",
    "pass": true,
    "gzip": 2320,
    "min": 6440,
    "behaviorPass": true,
    "cssPass": true,
    "total": 18,
    "failed": [],
    "error": null,
    "name": "r2-10-v10"
  },
  {
    "candidate": "harness/round2/assembled/r2-10-v11.svelte",
    "pass": false,
    "gzip": 2308,
    "min": 6394,
    "behaviorPass": false,
    "cssPass": true,
    "total": 18,
    "failed": [
      "with a body, reversing is ignored (no death, keeps direction)"
    ],
    "error": null,
    "name": "r2-10-v11"
  },
  {
    "candidate": "harness/round2/assembled/r2-10-v5.svelte",
    "pass": true,
    "gzip": 2338,
    "min": 6480,
    "behaviorPass": true,
    "cssPass": true,
    "total": 18,
    "failed": [],
    "error": null,
    "name": "r2-10-v5"
  },
  {
    "candidate": "harness/round2/assembled/r2-10-v7.svelte",
    "pass": true,
    "gzip": 2344,
    "min": 6478,
    "behaviorPass": true,
    "cssPass": true,
    "total": 18,
    "failed": [],
    "error": null,
    "name": "r2-10-v7"
  },
  {
    "candidate": "harness/round2/assembled/r2-10-v8.svelte",
    "pass": true,
    "gzip": 2336,
    "min": 6476,
    "behaviorPass": true,
    "cssPass": true,
    "total": 18,
    "failed": [],
    "error": null,
    "name": "r2-10-v8"
  },
  {
    "candidate": "harness/round2/assembled/r2-10-v9.svelte",
    "pass": true,
    "gzip": 2333,
    "min": 6482,
    "behaviorPass": true,
    "cssPass": true,
    "total": 18,
    "failed": [],
    "error": null,
    "name": "r2-10-v9"
  }
]